keycumber/__init__.py
tests/__init__.py
tests/test_keycumber.py
keycumber-1.0.5.dist-info/LICENSE
keycumber-1.0.5.dist-info/METADATA
keycumber-1.0.5.dist-info/WHEEL
keycumber-1.0.5.dist-info/entry_points.txt
keycumber-1.0.5.dist-info/top_level.txt
keycumber-1.0.5.dist-info/RECORD
