Metadata-Version: 2.1
Name: keycumber
Version: 1.0.5
Summary: 🥒 A Keyword Combinator to make Inbound Marketer's life better.
Home-page: https://github.com/louisguitton/keycumber
Author: Louis Guitton
Author-email: admin@guitton.co
License: UNKNOWN
Platform: UNKNOWN
Classifier: Programming Language :: Python :: 3
Classifier: License :: OSI Approved :: MIT License
Classifier: Operating System :: OS Independent
Requires-Python: >=3.6
Requires-Dist: pandas (>=1.0.1)
Requires-Dist: click (>=7.0)
Requires-Dist: click-completion
